alphacoders/__init__.py
alphacoders/__main__.py
alphacoders-1.1.0.dist-info/LICENSE
alphacoders-1.1.0.dist-info/METADATA
alphacoders-1.1.0.dist-info/WHEEL
alphacoders-1.1.0.dist-info/top_level.txt
alphacoders-1.1.0.dist-info/RECORD
