Metadata-Version: 2.1
Name: alphacoders
Version: 1.1.0
Summary: Download wallpapers from Alpha Coders
Home-page: https://github.com/whoiscc/alphacoders
Author: Correctizer
Author-email: correctizer@gmail.com
License: MIT
Platform: UNKNOWN
Classifier: License :: OSI Approved :: MIT License
Classifier: Programming Language :: Python :: 3
Classifier: Programming Language :: Python :: 3.7
Requires-Dist: aiohttp
Requires-Dist: lxml
